{
  "type": "FeatureCollection",
  "features": [
    {
      "type": "Feature",
      "properties": {
        "route_id": "632",
        "walk_limit_m": 400,
        "buffer_radius_m": 30,
        "node_count": 616
      },
      "geometry": {
        "type": "MultiPolygon",
        "coordinates": [
          [
            [
              [
                -113.44619197161501,
                53.49759958982233
              ],
              [
                -113.44641027245696,
                53.49761435299636
              ],
              [
                -113.44659112583032,
                53.49768873309873
              ],
              [
                -113.44682769990595,
                53.4978767507061
              ],
              [
                -113.44686237885244,
                53.498031884532736
              ],
              [
                -113.44671483631384,
                53.4981907899064
              ],
              [
                -113.44645491710435,
                53.498256657644085
              ],
              [
                -113.44633626863086,
                53.49846926277109
              ],
              [
                -113.44602325782844,
                53.49855461747416
              ],
              [
                -113.44599648348104,
                53.49876675431385
              ],
              [
                -113.44579112645242,
                53.4989081020715
              ],
              [
                -113.44572996670136,
                53.49903218337007
              ],
              [
                -113.44579902553528,
                53.49915824732595
              ],
              [
                -113.44632159630358,
                53.49942269550608
              ],
              [
                -113.4467040297407,
                53.49935275727503
              ],
              [
                -113.44710847909887,
                53.4995071372545
              ],
              [
                -113.44726405458593,
                53.49976348227265
              ],
              [
                -113.44721764866752,
                53.49992231872694
              ],
              [
                -113.44734045911153,
                53.500200381937404
              ],
              [
                -113.44730465137327,
                53.50034581550297
              ],
              [
                -113.44755735548495,
                53.500400767865855
              ],
              [
                -113.44772284892575,
                53.50055326087807
              ],
              [
                -113.4477300090936,
                53.500826980934114
              ],
              [
                -113.44763981655024,
                53.50094946401747
              ],
              [
                -113.4477340923611,
                53.501081254003935
              ],
              [
                -113.44794147070736,
                53.501004023636966
              ],
              [
                -113.44828763529006,
                53.500720915172444
              ],
              [
                -113.4485707673497,
                53.50065388629988
              ],
              [
                -113.44878560715193,
                53.50068133253597
              ],
              [
                -113.4489774846276,
                53.50078813109537
              ],
              [
                -113.4490381633254,
                53.50091403806893
              ],
              [
                -113.4489921312048,
                53.50104213249105
              ],
              [
                -113.44838236762509,
                53.50146218528905
              ],
              [
                -113.4477150844305,
                53.50166463105881
              ],
              [
                -113.44733997157499,
                53.50168434306358
              ],
              [
                -113.44703581214418,
                53.50161456038778
              ],
              [
                -113.4464777360652,
                53.50176820982759
              ],
              [
                -113.4459119496603,
                53.501691173149204
              ],
              [
                -113.44553004799194,
                53.5017542235947
              ],
              [
                -113.44527099111377,
                53.50169265361533
              ],
              [
                -113.44496031014451,
                53.50177561439065
              ],
              [
                -113.44474546703955,
                53.50174816131432
              ],
              [
                -113.44456714882607,
                53.5016538452907
              ],
              [
                -113.44436537954226,
                53.501693464349756
              ],
              [
                -113.44411798552952,
                53.50190664491593
              ],
              [
                -113.44390680355988,
                53.50194281459472
              ],
              [
                -113.4436664110061,
                53.50190692544346
              ],
              [
                -113.44337810521431,
                53.50208783121069
              ],
              [
                -113.44265835344936,
                53.50210015797054
              ],
              [
                -113.44246648551376,
                53.50199334917184
              ],
              [
                -113.44240738797565,
                53.5018362253595
              ],
              [
                -113.44203608879677,
                53.50168375928324
              ],
              [
                -113.44195132792667,
                53.501535636923464
              ],
              [
                -113.44210455993759,
                53.50132399945127
              ],
              [
                -113.44234348989583,
                53.501259187834464
              ],
              [
                -113.44261793970335,
                53.50127985731204
              ],
              [
                -113.44276734696933,
                53.50114591802492
              ],
              [
                -113.44264188950878,
                53.50103284857842
              ],
              [
                -113.4426235938775,
                53.50090230162118
              ],
              [
                -113.44286329044336,
                53.50066285636179
              ],
              [
                -113.44261372067999,
                53.50060792166323
              ],
              [
                -113.44244824514233,
                53.5004554213718
              ],
              [
                -113.44252927829133,
                53.500230026676476
              ],
              [
                -113.44286268782609,
                53.50010589632845
              ],
              [
                -113.44229930348192,
                53.499563047212895
              ],
              [
                -113.44228100967754,
                53.499432500154946
              ],
              [
                -113.44237738088202,
                53.4993056739667
              ],
              [
                -113.44218804991728,
                53.49895060031435
              ],
              [
                -113.44223040641276,
                53.49879614545229
              ],
              [
                -113.44240953900494,
                53.49868175189568
              ],
              [
                -113.44266506899856,
                53.498645976803665
              ],
              [
                -113.44288695769818,
                53.49869104366608
              ],
              [
                -113.44285264800426,
                53.49843618916157
              ],
              [
                -113.44262213476297,
                53.49838232159379
              ],
              [
                -113.44246891693983,
                53.49825524768632
              ],
              [
                -113.44249101291228,
                53.49804934625217
              ],
              [
                -113.44263289094809,
                53.49794932238718
              ],
              [
                -113.44286819749621,
                53.49789943811086
              ],
              [
                -113.44289263152433,
                53.497742036002236
              ],
              [
                -113.44305209093127,
                53.49761772330327
              ],
              [
                -113.4441052477622,
                53.49736176539155
              ],
              [
                -113.44432492299502,
                53.49736370269884
              ],
              [
                -113.44451712813387,
                53.49742715804251
              ],
              [
                -113.44463647298178,
                53.49753714618546
              ],
              [
                -113.44464547522868,
                53.49769356006663
              ],
              [
                -113.44443526494045,
                53.49785744468114
              ],
              [
                -113.44374950563797,
                53.49801680792906
              ],
              [
                -113.44375318186356,
                53.49819412974842
              ],
              [
                -113.44525586224167,
                53.49758323270133
              ],
              [
                -113.44560167716133,
                53.497576154015924
              ],
              [
                -113.4458711129179,
                53.49772160075096
              ],
              [
                -113.44619197161501,
                53.49759958982233
              ]
            ],
            [
              [
                -113.44436308181146,
                53.49872624236257
              ],
              [
                -113.44479464591495,
                53.49856114517783
              ],
              [
                -113.44496639440318,
                53.498411331561876
              ],
              [
                -113.44428560365746,
                53.49867828809275
              ],
              [
                -113.44436308181146,
                53.49872624236257
              ]
            ],
            [
              [
                -113.44597740715821,
                53.500911094417205
              ],
              [
                -113.44636665282381,
                53.50100073351932
              ],
              [
                -113.44653281497254,
                53.50118575063102
              ],
              [
                -113.44662594991148,
                53.50117728594728
              ],
              [
                -113.44670910596405,
                53.50095786350521
              ],
              [
                -113.4466622436186,
                53.500907048413566
              ],
              [
                -113.44633072822899,
                53.50083231079796
              ],
              [
                -113.44597740715821,
                53.500911094417205
              ]
            ],
            [
              [
                -113.4452327082136,
                53.500617508490976
              ],
              [
                -113.44537816554605,
                53.50046663539207
              ],
              [
                -113.4454646564141,
                53.50041566153928
              ],
              [
                -113.44517808778633,
                53.500524982288674
              ],
              [
                -113.4452327082136,
                53.500617508490976
              ]
            ],
            [
              [
                -113.44632256624584,
                53.49981584741957
              ],
              [
                -113.44617625071027,
                53.49986811357527
              ],
              [
                -113.44637713335806,
                53.49996458289049
              ],
              [
                -113.44640925134898,
                53.499916379906956
              ],
              [
                -113.44632256624584,
                53.49981584741957
              ]
            ],
            [
              [
                -113.44637487562599,
                53.50027177709606
              ],
              [
                -113.44626894001938,
                53.50033616974449
              ],
              [
                -113.4461473658486,
                53.50037305295261
              ],
              [
                -113.4463397717467,
                53.500438289991656
              ],
              [
                -113.44651106186349,
                53.50038032926614
              ],
              [
                -113.44637487562599,
                53.50027177709606
              ]
            ],
            [
              [
                -113.44512579646982,
                53.500858199882316
              ],
              [
                -113.44511708225727,
                53.50084376592891
              ],
              [
                -113.44508897719072,
                53.500860034994304
              ],
              [
                -113.44512579646982,
                53.500858199882316
              ]
            ],
            [
              [
                -113.44373242915096,
                53.500510014198966
              ],
              [
                -113.44378850022315,
                53.500432159697134
              ],
              [
                -113.44373344034862,
                53.50037509275592
              ],
              [
                -113.44373242915096,
                53.500510014198966
              ]
            ]
          ],
          [
            [
              [
                -113.44469395221321,
                53.50238032751667
              ],
              [
                -113.44503084478418,
                53.502333158242955
              ],
              [
                -113.44532500789998,
                53.50244183179307
              ],
              [
                -113.44540412612287,
                53.50264268942213
              ],
              [
                -113.44522185052479,
                53.50281807186231
              ],
              [
                -113.444884954353,
                53.5028652417119
              ],
              [
                -113.44459078936202,
                53.502756567105536
              ],
              [
                -113.44451167473996,
                53.50255570890062
              ],
              [
                -113.44469395221321,
                53.50238032751667
              ]
            ]
          ],
          [
            [
              [
                -113.44168661031836,
                53.51134482162305
              ],
              [
                -113.4419794794244,
                53.51129467734537
              ],
              [
                -113.44224570617195,
                53.511359840976716
              ],
              [
                -113.44261347361193,
                53.51129805974208
              ],
              [
                -113.44287424867089,
                53.51137127793326
              ],
              [
                -113.44301114101685,
                53.51147376249722
              ],
              [
                -113.44305197313591,
                53.51169813688822
              ],
              [
                -113.4432239038835,
                53.51179834882225
              ],
              [
                -113.44328458237652,
                53.51192425852071
              ],
              [
                -113.44316316325886,
                53.51211747012892
              ],
              [
                -113.44286844713628,
                53.51220190094805
              ],
              [
                -113.44305432472471,
                53.512348950342016
              ],
              [
                -113.44308343519191,
                53.51266103962476
              ],
              [
                -113.44328649620974,
                53.51285169568114
              ],
              [
                -113.4432441311559,
                53.513006150699326
              ],
              [
                -113.44302549418911,
                53.51313266991381
              ],
              [
                -113.44263880352788,
                53.51312925811046
              ],
              [
                -113.44240631188335,
                53.512966344316396
              ],
              [
                -113.44175809975297,
                53.51284345669241
              ],
              [
                -113.44154584525586,
                53.51271313400671
              ],
              [
                -113.44150297131726,
                53.51224468476895
              ],
              [
                -113.44161533336097,
                53.512083851608864
              ],
              [
                -113.44146207843615,
                53.511576984533114
              ],
              [
                -113.44168661031836,
                53.51134482162305
              ]
            ]
          ],
          [
            [
              [
                -113.44032601477176,
                53.522683797252846
              ],
              [
                -113.44065369328516,
                53.522617177952085
              ],
              [
                -113.44096444672523,
                53.52270814726649
              ],
              [
                -113.44107624174038,
                53.52290341725913
              ],
              [
                -113.44092358808538,
                53.523088601961966
              ],
              [
                -113.44059590640192,
                53.52315522203396
              ],
              [
                -113.44028515041762,
                53.52306425179509
              ],
              [
                -113.44017335857254,
                53.52286898103123
              ],
              [
                -113.44032601477176,
                53.522683797252846
              ]
            ]
          ],
          [
            [
              [
                -113.44164589760751,
                53.52306466051817
              ],
              [
                -113.44192317191225,
                53.52316059750231
              ],
              [
                -113.44218159201931,
                53.52305976532676
              ],
              [
                -113.44248444457101,
                53.523080242299294
              ],
              [
                -113.44265229490405,
                53.52316483838893
              ],
              [
                -113.44292720850056,
                53.52347539582875
              ],
              [
                -113.44290552779592,
                53.52373706219678
              ],
              [
                -113.44270869901725,
                53.52387574557948
              ],
              [
                -113.44236549869132,
                53.52390299539127
              ],
              [
                -113.44209687129334,
                53.52378353138615
              ],
              [
                -113.4418515752809,
                53.523904031487525
              ],
              [
                -113.44157040531944,
                53.52390583545709
              ],
              [
                -113.44179863970777,
                53.52403328994367
              ],
              [
                -113.44202712178131,
                53.52392876894894
              ],
              [
                -113.44233189028444,
                53.52393145805529
              ],
              [
                -113.44254050268765,
                53.52402653866532
              ],
              [
                -113.44262161588615,
                53.524148296896826
              ],
              [
                -113.44265405764106,
                53.52435371111482
              ],
              [
                -113.44258713534838,
                53.52447849518384
              ],
              [
                -113.44182908319479,
                53.5249023080615
              ],
              [
                -113.44208341151271,
                53.52512677894545
              ],
              [
                -113.44200233261053,
                53.52535217303761
              ],
              [
                -113.44174641026615,
                53.525450835033084
              ],
              [
                -113.4414843011227,
                53.52544084107959
              ],
              [
                -113.44116763673273,
                53.52528295440004
              ],
              [
                -113.4410675741156,
                53.5251679427271
              ],
              [
                -113.4408547970088,
                53.525338549072366
              ],
              [
                -113.4405991053537,
                53.52537432195997
              ],
              [
                -113.44032353473303,
                53.525304489859764
              ],
              [
                -113.44017130180744,
                53.52548740362014
              ],
              [
                -113.43984360047133,
                53.52555402182473
              ],
              [
                -113.43956375146927,
                53.52548203162604
              ],
              [
                -113.43942104009646,
                53.525298980415435
              ],
              [
                -113.43912748647917,
                53.52537191449182
              ],
              [
                -113.43883714534893,
                53.52531661416979
              ],
              [
                -113.43865987594504,
                53.52511172725345
              ],
              [
                -113.43880939201892,
                53.524902299774446
              ],
              [
                -113.43867754295844,
                53.52478603682917
              ],
              [
                -113.43865924696351,
                53.524655489717766
              ],
              [
                -113.43883298910788,
                53.52448422099767
              ],
              [
                -113.43865108482599,
                53.524277427122165
              ],
              [
                -113.43869717127704,
                53.524149336510426
              ],
              [
                -113.43884832011878,
                53.52404577905174
              ],
              [
                -113.43865148418244,
                53.52385768988402
              ],
              [
                -113.43874059146019,
                53.5236583179268
              ],
              [
                -113.43904017485619,
                53.52355488721371
              ],
              [
                -113.4392993651595,
                53.52358014740506
              ],
              [
                -113.4394857783107,
                53.5236818509939
              ],
              [
                -113.43972163685393,
                53.52357096594816
              ],
              [
                -113.43998411652285,
                53.52356560686999
              ],
              [
                -113.4401764352877,
                53.523629067689015
              ],
              [
                -113.44030810021944,
                53.52376448560464
              ],
              [
                -113.44029132410735,
                53.52392067150637
              ],
              [
                -113.44012972105608,
                53.52404576727811
              ],
              [
                -113.4402489124245,
                53.52411943084815
              ],
              [
                -113.44056436456351,
                53.52400228810808
              ],
              [
                -113.44091983869504,
                53.524065915559774
              ],
              [
                -113.44121926912393,
                53.52390225654214
              ],
              [
                -113.44094450263539,
                53.52371321833439
              ],
              [
                -113.44093235227707,
                53.52343958397143
              ],
              [
                -113.44101637365578,
                53.52325594435151
              ],
              [
                -113.44123506793342,
                53.523129428359596
              ],
              [
                -113.44164589760751,
                53.52306466051817
              ]
            ],
            [
              [
                -113.4394911270778,
                53.52495602159997
              ],
              [
                -113.43985660894893,
                53.52483168564518
              ],
              [
                -113.44007156649883,
                53.52485914614549
              ],
              [
                -113.44025233201006,
                53.52495563946627
              ],
              [
                -113.44034055499463,
                53.52489750989364
              ],
              [
                -113.44018127649086,
                53.524726195708084
              ],
              [
                -113.44020606743565,
                53.52459602979861
              ],
              [
                -113.44034503847463,
                53.524481490660015
              ],
              [
                -113.44024518758599,
                53.52441617033864
              ],
              [
                -113.43992973149835,
                53.5245333122729
              ],
              [
                -113.43967053502273,
                53.524508053521714
              ],
              [
                -113.43948799130945,
                53.52440991834126
              ],
              [
                -113.43937591081772,
                53.52448297839299
              ],
              [
                -113.43955781951006,
                53.52468977110934
              ],
              [
                -113.4394083078755,
                53.524899199482
              ],
              [
                -113.4394911270778,
                53.52495602159997
              ]
            ],
            [
              [
                -113.43948520877267,
                53.5241243828854
              ],
              [
                -113.43960797887414,
                53.52404643215997
              ],
              [
                -113.43948182169362,
                53.523966350236876
              ],
              [
                -113.43935477980266,
                53.52404452041953
              ],
              [
                -113.43948520877267,
                53.5241243828854
              ]
            ],
            [
              [
                -113.44108646794747,
                53.52451860984563
              ],
              [
                -113.44090876142467,
                53.5244786086825
              ],
              [
                -113.4410318793169,
                53.5245678810387
              ],
              [
                -113.44108646794747,
                53.52451860984563
              ]
            ],
            [
              [
                -113.44103252074254,
                53.52481292031467
              ],
              [
                -113.44091714496592,
                53.52489838941724
              ],
              [
                -113.44106772594215,
                53.525042258889755
              ],
              [
                -113.44118645270554,
                53.52491525069181
              ],
              [
                -113.44103252074254,
                53.52481292031467
              ]
            ]
          ],
          [
            [
              [
                -113.44041728166604,
                53.5325065209254
              ],
              [
                -113.44062165062154,
                53.53245818861956
              ],
              [
                -113.44084012957653,
                53.53247295991053
              ],
              [
                -113.44102112395939,
                53.532547346496635
              ],
              [
                -113.44112189092405,
                53.532663781671076
              ],
              [
                -113.44111863309932,
                53.53279476861649
              ],
              [
                -113.44098326844994,
                53.532926060220994
              ],
              [
                -113.44111303635701,
                53.53304125519571
              ],
              [
                -113.4411220372781,
                53.53319766855335
              ],
              [
                -113.44101552217069,
                53.533312273733216
              ],
              [
                -113.4407882252648,
                53.53339073539342
              ],
              [
                -113.44044645343047,
                53.5333574398676
              ],
              [
                -113.44024430358792,
                53.53318991677438
              ],
              [
                -113.44024756410523,
                53.53305892983027
              ],
              [
                -113.44038293146896,
                53.532927639031605
              ],
              [
                -113.44025316587692,
                53.53281244323608
              ],
              [
                -113.44023486080272,
                53.53268189661913
              ],
              [
                -113.44041728166604,
                53.5325065209254
              ]
            ]
          ],
          [
            [
              [
                -113.43879472268301,
                53.52258259333138
              ],
              [
                -113.43912240295587,
                53.52251597821059
              ],
              [
                -113.43943315249057,
                53.52260695155356
              ],
              [
                -113.43954494022303,
                53.52280222306347
              ],
              [
                -113.43939228017408,
                53.52298740588348
              ],
              [
                -113.43906459673103,
                53.523054021775415
              ],
              [
                -113.43875384465234,
                53.52296304750796
              ],
              [
                -113.43864206009005,
                53.52276777522689
              ],
              [
                -113.43879472268301,
                53.52258259333138
              ]
            ]
          ],
          [
            [
              [
                -113.43689522875295,
                53.523035584970316
              ],
              [
                -113.43721944554235,
                53.52310797520235
              ],
              [
                -113.43743612743445,
                53.52325846663
              ],
              [
                -113.43749680630341,
                53.52338437905549
              ],
              [
                -113.43745071697265,
                53.52351246925042
              ],
              [
                -113.43730636102542,
                53.5236134058439
              ],
              [
                -113.43727721759659,
                53.52390788226811
              ],
              [
                -113.43708639338558,
                53.524044234505766
              ],
              [
                -113.43729151570201,
                53.52426057972883
              ],
              [
                -113.43712134010595,
                53.52448020013544
              ],
              [
                -113.43726966006942,
                53.524604769716696
              ],
              [
                -113.43728795176902,
                53.52473531708977
              ],
              [
                -113.43712963161231,
                53.52489926434679
              ],
              [
                -113.43727306423895,
                53.52502136966325
              ],
              [
                -113.43730047880693,
                53.52518261872037
              ],
              [
                -113.43758248154603,
                53.52509158646976
              ],
              [
                -113.4378805183146,
                53.525129665776916
              ],
              [
                -113.43808261954683,
                53.525297193607585
              ],
              [
                -113.43801067578808,
                53.525514676276465
              ],
              [
                -113.43828222020164,
                53.52552306315971
              ],
              [
                -113.43851494562234,
                53.525640362938624
              ],
              [
                -113.43857563130376,
                53.52576627469665
              ],
              [
                -113.43852954288148,
                53.525894365253485
              ],
              [
                -113.43822689013832,
                53.52603793828193
              ],
              [
                -113.4378764140885,
                53.526001031322224
              ],
              [
                -113.43756227304321,
                53.52603933725379
              ],
              [
                -113.43732653741705,
                53.525970325986464
              ],
              [
                -113.4371838286773,
                53.5257560700738
              ],
              [
                -113.43735032400255,
                53.525564336023805
              ],
              [
                -113.43721551092423,
                53.525448050329246
              ],
              [
                -113.4368675722437,
                53.52555721493625
              ],
              [
                -113.43657723261096,
                53.525501909106254
              ],
              [
                -113.4364193280848,
                53.525365275051335
              ],
              [
                -113.43621654722631,
                53.52544923863364
              ],
              [
                -113.43595405517726,
                53.52545458956976
              ],
              [
                -113.4357308127312,
                53.5253721392059
              ],
              [
                -113.43549337911952,
                53.525161898486616
              ],
              [
                -113.43552777178205,
                53.524981425746326
              ],
              [
                -113.43574649147102,
                53.52485491955141
              ],
              [
                -113.43612003077499,
                53.52485326589027
              ],
              [
                -113.43642722752047,
                53.525005595934445
              ],
              [
                -113.43655676830605,
                53.524900934973616
              ],
              [
                -113.43639307285429,
                53.52472738152808
              ],
              [
                -113.43641787544513,
                53.52459721627504
              ],
              [
                -113.43655955982199,
                53.524481399211325
              ],
              [
                -113.43638794492225,
                53.52425256688095
              ],
              [
                -113.43660660666751,
                53.524038865019854
              ],
              [
                -113.43617752466783,
                53.52372251667183
              ],
              [
                -113.4361323544673,
                53.52336336580632
              ],
              [
                -113.43631976220097,
                53.523161710672625
              ],
              [
                -113.43689522875295,
                53.523035584970316
              ]
            ]
          ],
          [
            [
              [
                -113.43657080548539,
                53.526424888073365
              ],
              [
                -113.43689851892488,
                53.52635827872038
              ],
              [
                -113.43720929227196,
                53.52644925753241
              ],
              [
                -113.43732108051387,
                53.52664453100909
              ],
              [
                -113.43716839737232,
                53.526829711141474
              ],
              [
                -113.43684068076173,
                53.526896321265625
              ],
              [
                -113.4365299048703,
                53.52680534152889
              ],
              [
                -113.4364181197995,
                53.52661006728104
              ],
              [
                -113.43657080548539,
                53.526424888073365
              ]
            ]
          ],
          [
            [
              [
                -113.43570424441668,
                53.52928769360594
              ],
              [
                -113.43593312074924,
                53.529370860919435
              ],
              [
                -113.43604187874547,
                53.52951332092354
              ],
              [
                -113.43599947250888,
                53.52966777345827
              ],
              [
                -113.43582019415106,
                53.52978215851245
              ],
              [
                -113.43556447124958,
                53.529817920948766
              ],
              [
                -113.43526784848618,
                53.529771133248715
              ],
              [
                -113.43493139958605,
                53.52956678862464
              ],
              [
                -113.43472772264965,
                53.529677082019695
              ],
              [
                -113.43446131463139,
                53.52969696455232
              ],
              [
                -113.43456385625066,
                53.52987547114665
              ],
              [
                -113.43491823750632,
                53.529760784879294
              ],
              [
                -113.4351332172129,
                53.529788253999584
              ],
              [
                -113.43530108017096,
                53.52987286019577
              ],
              [
                -113.43537089644337,
                53.530099590087794
              ],
              [
                -113.43516049321914,
                53.53026345975895
              ],
              [
                -113.43490476682878,
                53.53029922081949
              ],
              [
                -113.43469533888798,
                53.530259328658026
              ],
              [
                -113.43454220253714,
                53.53016532581739
              ],
              [
                -113.43448194207868,
                53.530022630270686
              ],
              [
                -113.43429942219855,
                53.530113282680794
              ],
              [
                -113.43408316169092,
                53.530136920684015
              ],
              [
                -113.43387373528356,
                53.53009702706421
              ],
              [
                -113.43372060131736,
                53.530003023141646
              ],
              [
                -113.43366439371283,
                53.52983068342976
              ],
              [
                -113.4335040292964,
                53.52968079166664
              ],
              [
                -113.43353843349948,
                53.52950031948883
              ],
              [
                -113.43375718210805,
                53.529373816697145
              ],
              [
                -113.43410171185148,
                53.52936647372053
              ],
              [
                -113.4343530795526,
                53.52918631765331
              ],
              [
                -113.43456933506543,
                53.52916267921384
              ],
              [
                -113.43478355256167,
                53.529204542925015
              ],
              [
                -113.43482837114762,
                53.52913766570888
              ],
              [
                -113.43461432706005,
                53.52904153876406
              ],
              [
                -113.43453019629696,
                53.52886696041329
              ],
              [
                -113.43462154942813,
                53.52868078067144
              ],
              [
                -113.43483951543774,
                53.528554239915906
              ],
              [
                -113.43513934684492,
                53.528521464156455
              ],
              [
                -113.43543366904996,
                53.52863015988355
              ],
              [
                -113.43551780301065,
                53.5288047375684
              ],
              [
                -113.43537562693513,
                53.529016133811716
              ],
              [
                -113.43558967257486,
                53.529112259375545
              ],
              [
                -113.43570424441668,
                53.52928769360594
              ]
            ]
          ],
          [
            [
              [
                -113.43608895001583,
                53.530213665913195
              ],
              [
                -113.43635841994497,
                53.530379072388385
              ],
              [
                -113.4363767118925,
                53.53050961978903
              ],
              [
                -113.43628955643827,
                53.53062988983111
              ],
              [
                -113.4360762655323,
                53.53072123840627
              ],
              [
                -113.43564950393915,
                53.530748631144085
              ],
              [
                -113.43548293226411,
                53.530826380687515
              ],
              [
                -113.43517526844666,
                53.53084075202042
              ],
              [
                -113.43516436838159,
                53.53086871639487
              ],
              [
                -113.4354406631695,
                53.53086011105363
              ],
              [
                -113.43569158800094,
                53.53096325893249
              ],
              [
                -113.4358772972256,
                53.5312508213445
              ],
              [
                -113.43581337708592,
                53.531428416380926
              ],
              [
                -113.4352854642608,
                53.53167233935218
              ],
              [
                -113.43506634873901,
                53.53168323578113
              ],
              [
                -113.43476143186575,
                53.53161422882314
              ],
              [
                -113.43460829038595,
                53.53152022614279
              ],
              [
                -113.43445251419259,
                53.53128569531769
              ],
              [
                -113.43455742617567,
                53.531043555835645
              ],
              [
                -113.43425868754623,
                53.53093011847078
              ],
              [
                -113.4341270187582,
                53.53079469407108
              ],
              [
                -113.43423113417941,
                53.530481979621584
              ],
              [
                -113.43451232003554,
                53.53036155865378
              ],
              [
                -113.43473216627389,
                53.530363511691014
              ],
              [
                -113.43492475484065,
                53.530427131804004
              ],
              [
                -113.43510826993831,
                53.53033561898545
              ],
              [
                -113.43539529789969,
                53.53031836912438
              ],
              [
                -113.43560313727652,
                53.530230861153825
              ],
              [
                -113.43608895001583,
                53.530213665913195
              ]
            ]
          ],
          [
            [
              [
                -113.43814300763921,
                53.53025281553632
              ],
              [
                -113.43855571025864,
                53.53020297856575
              ],
              [
                -113.43883558901732,
                53.530274970744735
              ],
              [
                -113.4389789811883,
                53.530462772619835
              ],
              [
                -113.43885749192891,
                53.53065598011534
              ],
              [
                -113.43854228579694,
                53.53074141436579
              ],
              [
                -113.4380983075546,
                53.53066872818032
              ],
              [
                -113.43795557839611,
                53.53045447356318
              ],
              [
                -113.43814300763921,
                53.53025281553632
              ]
            ]
          ],
          [
            [
              [
                -113.43523687299681,
                53.53181178525683
              ],
              [
                -113.43556462999375,
                53.531745179129956
              ],
              [
                -113.43587544041446,
                53.53183616092801
              ],
              [
                -113.43598723752943,
                53.53203143540161
              ],
              [
                -113.43583452986184,
                53.532216613957914
              ],
              [
                -113.43550676969264,
                53.53228322085606
              ],
              [
                -113.4351959567269,
                53.53219223813307
              ],
              [
                -113.43508416278421,
                53.5319969628882
              ],
              [
                -113.43523687299681,
                53.53181178525683
              ]
            ]
          ],
          [
            [
              [
                -113.43560566727464,
                53.53236658625934
              ],
              [
                -113.43597754733956,
                53.53230296378419
              ],
              [
                -113.43632689824494,
                53.53244515689838
              ],
              [
                -113.43654197369457,
                53.53288983445922
              ],
              [
                -113.43667894562734,
                53.53300867098646
              ],
              [
                -113.43668077574087,
                53.533178418716716
              ],
              [
                -113.43676047419217,
                53.53321099431484
              ],
              [
                -113.43694394661043,
                53.53311952222301
              ],
              [
                -113.43716022051471,
                53.533095878901875
              ],
              [
                -113.43749870029978,
                53.53320755328918
              ],
              [
                -113.43758351247563,
                53.533355677557005
              ],
              [
                -113.4375084717997,
                53.533513326694155
              ],
              [
                -113.43774884626264,
                53.5335979555806
              ],
              [
                -113.43785762158835,
                53.533740413651195
              ],
              [
                -113.43781521824077,
                53.53389486670366
              ],
              [
                -113.4376732111306,
                53.53399488576514
              ],
              [
                -113.43742458056792,
                53.53404541444003
              ],
              [
                -113.43720397460108,
                53.534016101074606
              ],
              [
                -113.43697965613136,
                53.53415027795634
              ],
              [
                -113.43663354107434,
                53.534157334985736
              ],
              [
                -113.43638042615034,
                53.53401651830308
              ],
              [
                -113.43636260040005,
                53.53382146658859
              ],
              [
                -113.43599702875453,
                53.533636916958415
              ],
              [
                -113.43601832164299,
                53.53338056325687
              ],
              [
                -113.43590240962365,
                53.533350357798454
              ],
              [
                -113.43576353865194,
                53.5334847140004
              ],
              [
                -113.43552441829745,
                53.533549514273595
              ],
              [
                -113.43530593533228,
                53.5335347333082
              ],
              [
                -113.43509729132053,
                53.53343964054715
              ],
              [
                -113.43501314928996,
                53.53326506277327
              ],
              [
                -113.43513400166002,
                53.53309831063439
              ],
              [
                -113.4353613078116,
                53.533019859625725
              ],
              [
                -113.43570299239757,
                53.533053143049834
              ],
              [
                -113.4357248578993,
                53.533015761377
              ],
              [
                -113.43545598889835,
                53.532604578905364
              ],
              [
                -113.43548079821741,
                53.53247441392047
              ],
              [
                -113.43560566727464,
                53.53236658625934
              ]
            ],
            [
              [
                -113.43703152066192,
                53.533627923196285
              ],
              [
                -113.43703192617369,
                53.533627573020354
              ],
              [
                -113.43703159544471,
                53.533627530771355
              ],
              [
                -113.43703152066192,
                53.533627923196285
              ]
            ]
          ],
          [
            [
              [
                -113.43760545685981,
                53.532509691381975
              ],
              [
                -113.43788881713978,
                53.53244268559565
              ],
              [
                -113.43814265694434,
                53.53248296506719
              ],
              [
                -113.43835280989339,
                53.532676511916954
              ],
              [
                -113.4382543704297,
                53.53288244298881
              ],
              [
                -113.4386057443916,
                53.532873762728784
              ],
              [
                -113.43885885961677,
                53.5330145747166
              ],
              [
                -113.43888423385398,
                53.53319557678173
              ],
              [
                -113.43868956362103,
                53.533353388497
              ],
              [
                -113.43881114558485,
                53.53346446334951
              ],
              [
                -113.43882013816223,
                53.533620876964
              ],
              [
                -113.43857026362912,
                53.5337968753908
              ],
              [
                -113.43830986588819,
                53.533817537490904
              ],
              [
                -113.43807408546985,
                53.53374852827612
              ],
              [
                -113.43793438090681,
                53.53358708829405
              ],
              [
                -113.43798398578004,
                53.5334248867641
              ],
              [
                -113.4377832890315,
                53.533373112123286
              ],
              [
                -113.4376463367993,
                53.533270622560735
              ],
              [
                -113.4376116586069,
                53.53311548684136
              ],
              [
                -113.43774559988962,
                53.53296454550955
              ],
              [
                -113.43753690547739,
                53.53286944790506
              ],
              [
                -113.43745209448872,
                53.53272132358048
              ],
              [
                -113.43760545685981,
                53.532509691381975
              ]
            ]
          ],
          [
            [
              [
                -113.43690908832343,
                53.5342599131509
              ],
              [
                -113.4372021207863,
                53.53420977893211
              ],
              [
                -113.437482023998,
                53.534281773967926
              ],
              [
                -113.4376254243293,
                53.53446957726775
              ],
              [
                -113.43751631385209,
                53.534654052936645
              ],
              [
                -113.43774052238562,
                53.53470748852852
              ],
              [
                -113.43787028688523,
                53.53480166634809
              ],
              [
                -113.43815847959384,
                53.53463071602208
              ],
              [
                -113.4384071126432,
                53.53458018579639
              ],
              [
                -113.43869751703043,
                53.53463548638376
              ],
              [
                -113.43885085852105,
                53.5347625630793
              ],
              [
                -113.43886916174891,
                53.53501690988878
              ],
              [
                -113.43875332719328,
                53.53515737989053
              ],
              [
                -113.43852601618748,
                53.535235837382906
              ],
              [
                -113.4381078721864,
                53.535234648701916
              ],
              [
                -113.43831112469445,
                53.535503591683806
              ],
              [
                -113.43837987940749,
                53.535896025881776
              ],
              [
                -113.43828771047886,
                53.5360425830896
              ],
              [
                -113.43807439713615,
                53.53613393541079
              ],
              [
                -113.43772877131894,
                53.53612075058282
              ],
              [
                -113.43750002828342,
                53.53596583374658
              ],
              [
                -113.43737658996199,
                53.53541934386381
              ],
              [
                -113.43705207782193,
                53.535197705273255
              ],
              [
                -113.437014031242,
                53.53490437054128
              ],
              [
                -113.43712248415393,
                53.53474634694669
              ],
              [
                -113.4368643731367,
                53.53467582526007
              ],
              [
                -113.43673268411759,
                53.534540404031254
              ],
              [
                -113.43674947631924,
                53.53438421869024
              ],
              [
                -113.43690908832343,
                53.5342599131509
              ]
            ]
          ],
          [
            [
              [
                -113.43258470877403,
                53.52503471440758
              ],
              [
                -113.43322605352985,
                53.5250143651168
              ],
              [
                -113.43380424555818,
                53.52510916881226
              ],
              [
                -113.43398519612157,
                53.525183566625074
              ],
              [
                -113.43409195593469,
                53.52540512898381
              ],
              [
                -113.43397613066021,
                53.52554559444581
              ],
              [
                -113.43374282608839,
                53.52562470222018
              ],
              [
                -113.43375252980205,
                53.52587308163676
              ],
              [
                -113.43344986066506,
                53.52601664274516
              ],
              [
                -113.43318774940656,
                53.52600663061192
              ],
              [
                -113.43299869370483,
                53.52592616577836
              ],
              [
                -113.43271478855874,
                53.52601851630049
              ],
              [
                -113.43228315156725,
                53.52596818346523
              ],
              [
                -113.43203339096054,
                53.526143986722666
              ],
              [
                -113.43164658146601,
                53.52614054066149
              ],
              [
                -113.43141791522521,
                53.52598561110228
              ],
              [
                -113.43144007509008,
                53.52577971182941
              ],
              [
                -113.43174274952156,
                53.52563615574938
              ],
              [
                -113.43209817573504,
                53.52567511934165
              ],
              [
                -113.4321334724589,
                53.52557380691166
              ],
              [
                -113.43210742566197,
                53.525520422357395
              ],
              [
                -113.43184592170977,
                53.52561364425478
              ],
              [
                -113.43151013560606,
                53.52562933398589
              ],
              [
                -113.43119173411867,
                53.52549841457739
              ],
              [
                -113.43106017148453,
                53.52529089853907
              ],
              [
                -113.4310753612276,
                53.52502759510002
              ],
              [
                -113.43121099808016,
                53.52489616088205
              ],
              [
                -113.43106497640028,
                53.52475348219349
              ],
              [
                -113.43109938766109,
                53.524573010510764
              ],
              [
                -113.43135938367044,
                53.52443675523501
              ],
              [
                -113.43170491279359,
                53.52444995958738
              ],
              [
                -113.43194582227328,
                53.524630316196905
              ],
              [
                -113.43194253595092,
                53.524761303361075
              ],
              [
                -113.43180690180834,
                53.524892738382086
              ],
              [
                -113.4319433314877,
                53.525015501031646
              ],
              [
                -113.43216078351807,
                53.52508218791116
              ],
              [
                -113.43228673255206,
                53.525205794198186
              ],
              [
                -113.43258470877403,
                53.52503471440758
              ]
            ]
          ],
          [
            [
              [
                -113.4342900352738,
                53.52592367915292
              ],
              [
                -113.43456987865167,
                53.52599568176422
              ],
              [
                -113.43470153346462,
                53.52613110592565
              ],
              [
                -113.43466713650183,
                53.52631157844587
              ],
              [
                -113.43443402237182,
                53.52646144777863
              ],
              [
                -113.43449622024899,
                53.5265292746403
              ],
              [
                -113.4347733562568,
                53.52636935978512
              ],
              [
                -113.43511890188944,
                53.52638255407478
              ],
              [
                -113.43534758360657,
                53.52653747636808
              ],
              [
                -113.43532544244624,
                53.526743376134625
              ],
              [
                -113.43514617434907,
                53.52685776011143
              ],
              [
                -113.43493486073321,
                53.52689391526258
              ],
              [
                -113.43468105736616,
                53.52685362853676
              ],
              [
                -113.43449587979195,
                53.52671852685823
              ],
              [
                -113.4343367484642,
                53.52684219406555
              ],
              [
                -113.43413239886344,
                53.5268905154436
              ],
              [
                -113.4339139506677,
                53.526875731531135
              ],
              [
                -113.43371766899843,
                53.52678986274035
              ],
              [
                -113.43342339440768,
                53.52688951584755
              ],
              [
                -113.43311018643783,
                53.526845191606526
              ],
              [
                -113.43308673960573,
                53.526979796841495
              ],
              [
                -113.43296393296606,
                53.52708643428329
              ],
              [
                -113.43310069516292,
                53.527205184301586
              ],
              [
                -113.433141244529,
                53.52742533608506
              ],
              [
                -113.43336864868026,
                53.52738298446154
              ],
              [
                -113.43363682286709,
                53.52742918139461
              ],
              [
                -113.4337901128113,
                53.52722048105996
              ],
              [
                -113.4341619509113,
                53.527156864656234
              ],
              [
                -113.43445626111192,
                53.52726556294659
              ],
              [
                -113.43453108981628,
                53.5274783414956
              ],
              [
                -113.43482662604228,
                53.52734245874405
              ],
              [
                -113.43516834536688,
                53.52737577096102
              ],
              [
                -113.43534181610728,
                53.52749328723692
              ],
              [
                -113.4353764807795,
                53.52764842389212
              ],
              [
                -113.43522879530232,
                53.527807315987296
              ],
              [
                -113.43494546135308,
                53.52787431521604
              ],
              [
                -113.43459028885974,
                53.52778293616645
              ],
              [
                -113.43448780838455,
                53.52754946000205
              ],
              [
                -113.43423494347866,
                53.52767804101565
              ],
              [
                -113.43386860656842,
                53.52765798634057
              ],
              [
                -113.43385624971818,
                53.527823393988406
              ],
              [
                -113.43367792596706,
                53.527954912439995
              ],
              [
                -113.43397359315514,
                53.52798888568132
              ],
              [
                -113.43418242301888,
                53.52782793855952
              ],
              [
                -113.43448224987021,
                53.52779516449658
              ],
              [
                -113.43477656534576,
                53.527903861929005
              ],
              [
                -113.43485568512286,
                53.528104725787344
              ],
              [
                -113.4347685300484,
                53.528224994757416
              ],
              [
                -113.43459651559748,
                53.52830658235271
              ],
              [
                -113.43418080888038,
                53.5282936151264
              ],
              [
                -113.43413921940505,
                53.52835312784047
              ],
              [
                -113.43433982017748,
                53.528431265432545
              ],
              [
                -113.43444055885047,
                53.528547706626746
              ],
              [
                -113.43435943321613,
                53.52877309593967
              ],
              [
                -113.43414614725579,
                53.52886444103828
              ],
              [
                -113.43390848983718,
                53.52887296398674
              ],
              [
                -113.43386306035683,
                53.52900588086693
              ],
              [
                -113.43372105978523,
                53.52910589522861
              ],
              [
                -113.43338394201592,
                53.5291530349247
              ],
              [
                -113.43306550811741,
                53.5290221209383
              ],
              [
                -113.43300549670616,
                53.52886975464614
              ],
              [
                -113.4330948891422,
                53.52872560200289
              ],
              [
                -113.43277251105812,
                53.528594419953755
              ],
              [
                -113.43250437131701,
                53.528138461639266
              ],
              [
                -113.43228842481413,
                53.52795349805084
              ],
              [
                -113.43215438282519,
                53.52807842380784
              ],
              [
                -113.43191528694439,
                53.528143216635605
              ],
              [
                -113.43169683293068,
                53.52812842873626
              ],
              [
                -113.43148822377883,
                53.52803332920995
              ],
              [
                -113.43136194571159,
                53.527720499964786
              ],
              [
                -113.43140805767015,
                53.527592411945655
              ],
              [
                -113.43155201788362,
                53.52749164533437
              ],
              [
                -113.43135354088346,
                53.52730286295253
              ],
              [
                -113.431440823339,
                53.52710510742759
              ],
              [
                -113.43121533727235,
                53.52714671599492
              ],
              [
                -113.43096153567001,
                53.52710642134842
              ],
              [
                -113.43078807847822,
                53.52698889855462
              ],
              [
                -113.43075343115596,
                53.52683376036034
              ],
              [
                -113.43086927058005,
                53.526693297891974
              ],
              [
                -113.43109655092745,
                53.52661485521191
              ],
              [
                -113.4314426683468,
                53.526649990023046
              ],
              [
                -113.43178895917816,
                53.52654228410761
              ],
              [
                -113.43215734492173,
                53.52664357532269
              ],
              [
                -113.43229113107695,
                53.52661458874325
              ],
              [
                -113.43224076648812,
                53.52636810158585
              ],
              [
                -113.43236562640097,
                53.52626027731768
              ],
              [
                -113.43256104299887,
                53.52620025655143
              ],
              [
                -113.4329027515205,
                53.52623357537499
              ],
              [
                -113.43310492000333,
                53.52640137567543
              ],
              [
                -113.43339264117805,
                53.5263532793213
              ],
              [
                -113.43365394546487,
                53.52641593804893
              ],
              [
                -113.43361973459115,
                53.5262614710311
              ],
              [
                -113.43375548956439,
                53.52606460301043
              ],
              [
                -113.43392749671645,
                53.52598301668095
              ],
              [
                -113.4342900352738,
                53.52592367915292
              ]
            ],
            [
              [
                -113.43333744348324,
                53.52799933492442
              ],
              [
                -113.43338408126927,
                53.528059050103714
              ],
              [
                -113.4334923223324,
                53.52799809735483
              ],
              [
                -113.43342595178265,
                53.528002715514226
              ],
              [
                -113.43333744348324,
                53.52799933492442
              ]
            ],
            [
              [
                -113.43354793688083,
                53.52861850833587
              ],
              [
                -113.4335483634532,
                53.52860147984649
              ],
              [
                -113.43352610880949,
                53.528620697816635
              ],
              [
                -113.43354793688083,
                53.52861850833587
              ]
            ],
            [
              [
                -113.43223130180938,
                53.5273513518185
              ],
              [
                -113.43206408197119,
                53.52748695412593
              ],
              [
                -113.43222592566455,
                53.52759969787387
              ],
              [
                -113.43228607529271,
                53.52779370350671
              ],
              [
                -113.43223130180938,
                53.5273513518185
              ]
            ],
            [
              [
                -113.43224244842462,
                53.527205714835304
              ],
              [
                -113.4322934859334,
                53.52714541052576
              ],
              [
                -113.432182443703,
                53.52712201579788
              ],
              [
                -113.43221382142464,
                53.52715569795557
              ],
              [
                -113.43224244842462,
                53.527205714835304
              ]
            ]
          ],
          [
            [
              [
                -113.43344783505955,
                53.53352117631953
              ],
              [
                -113.43378415880434,
                53.53369778122538
              ],
              [
                -113.43374596795647,
                53.5339209338383
              ],
              [
                -113.43390312093793,
                53.53396916561292
              ],
              [
                -113.43412299050239,
                53.53377873900989
              ],
              [
                -113.43445096121259,
                53.53374955516348
              ],
              [
                -113.43486980927814,
                53.53361305920658
              ],
              [
                -113.43517273438368,
                53.53363355387718
              ],
              [
                -113.43548471278673,
                53.533771859356726
              ],
              [
                -113.43556384771904,
                53.53397272240645
              ],
              [
                -113.43541614167579,
                53.53413161481676
              ],
              [
                -113.43517701715302,
                53.53419641443495
              ],
              [
                -113.43470812848528,
                53.53417653543953
              ],
              [
                -113.43494433573288,
                53.53424558039623
              ],
              [
                -113.43507601815942,
                53.53438100367549
              ],
              [
                -113.43505921978935,
                53.53453718885
              ],
              [
                -113.43489960126863,
                53.53466149198543
              ],
              [
                -113.43460656280341,
                53.53471162062009
              ],
              [
                -113.4343266614018,
                53.53463961883169
              ],
              [
                -113.43418327495345,
                53.53445181142248
              ],
              [
                -113.43427716950961,
                53.534278064371286
              ],
              [
                -113.43406818103654,
                53.53422273541674
              ],
              [
                -113.43395220049011,
                53.53436389349961
              ],
              [
                -113.43372488452391,
                53.53444234192114
              ],
              [
                -113.43346272109417,
                53.53443233098424
              ],
              [
                -113.43325407663552,
                53.53433723502147
              ],
              [
                -113.43316927741193,
                53.53418910755717
              ],
              [
                -113.43323143002277,
                53.53404376578288
              ],
              [
                -113.4330161334353,
                53.53396283214744
              ],
              [
                -113.43291538530865,
                53.53384638994863
              ],
              [
                -113.43298596293752,
                53.53363012342398
              ],
              [
                -113.43276906171931,
                53.533563514832295
              ],
              [
                -113.43264964299084,
                53.53345351622709
              ],
              [
                -113.43269331402213,
                53.53322447495192
              ],
              [
                -113.43297452229216,
                53.533104057402234
              ],
              [
                -113.43331628688287,
                53.53313737438559
              ],
              [
                -113.43350615520961,
                53.53327948225666
              ],
              [
                -113.43344783505955,
                53.53352117631953
              ]
            ]
          ],
          [
            [
              [
                -113.43429407707413,
                53.534798168164855
              ],
              [
                -113.43447507033758,
                53.534872564655714
              ],
              [
                -113.43457582523038,
                53.53498900544656
              ],
              [
                -113.43457254723197,
                53.53511999239371
              ],
              [
                -113.43446600958123,
                53.535234591952936
              ],
              [
                -113.43423868998019,
                53.53531304138265
              ],
              [
                -113.43386288548075,
                53.53533739271914
              ],
              [
                -113.43359228635504,
                53.53544864197722
              ],
              [
                -113.4332401989593,
                53.5354110905332
              ],
              [
                -113.43312940630206,
                53.53553749568124
              ],
              [
                -113.43290208254341,
                53.53561594261054
              ],
              [
                -113.4326399119888,
                53.53560592994905
              ],
              [
                -113.43245891868742,
                53.53553153068629
              ],
              [
                -113.43234646463128,
                53.535362704583186
              ],
              [
                -113.43242840365104,
                53.53519912181073
              ],
              [
                -113.43226951020014,
                53.53515751290903
              ],
              [
                -113.43218128094841,
                53.535283301806025
              ],
              [
                -113.43200923320667,
                53.535364885962665
              ],
              [
                -113.43124874216048,
                53.53545401561179
              ],
              [
                -113.43073933419433,
                53.53543343934589
              ],
              [
                -113.43057145778141,
                53.53534882695757
              ],
              [
                -113.43048959503659,
                53.53522162155654
              ],
              [
                -113.43030849533943,
                53.53539319626289
              ],
              [
                -113.43054018439449,
                53.53554889259319
              ],
              [
                -113.4304964997118,
                53.53577793315575
              ],
              [
                -113.43029922577193,
                53.53588128870824
              ],
              [
                -113.42996406774397,
                53.53591831736265
              ],
              [
                -113.42974659598994,
                53.53610166980844
              ],
              [
                -113.42947526863146,
                53.53613636624311
              ],
              [
                -113.4293873795018,
                53.53633991020137
              ],
              [
                -113.42908768249214,
                53.53644331777621
              ],
              [
                -113.42886918646434,
                53.536428525190566
              ],
              [
                -113.42868819604327,
                53.53635412019223
              ],
              [
                -113.42858745379849,
                53.53623767431881
              ],
              [
                -113.42859075026377,
                53.53610668735229
              ],
              [
                -113.42876391895182,
                53.535957194858504
              ],
              [
                -113.42907253423334,
                53.53590813389332
              ],
              [
                -113.4291352026307,
                53.5357263636759
              ],
              [
                -113.4294139351224,
                53.53560638220994
              ],
              [
                -113.42958132535524,
                53.53544346246041
              ],
              [
                -113.42930952526824,
                53.53550466179415
              ],
              [
                -113.42912477844814,
                53.53569190497182
              ],
              [
                -113.42887612726196,
                53.53574241607258
              ],
              [
                -113.4285209008667,
                53.53565101968099
              ],
              [
                -113.42841242810057,
                53.5354384391695
              ],
              [
                -113.42826765403542,
                53.53543492992834
              ],
              [
                -113.42821339104975,
                53.53564204060445
              ],
              [
                -113.42788847387119,
                53.53576721849715
              ],
              [
                -113.42755382185678,
                53.53571408925589
              ],
              [
                -113.42738025026226,
                53.53553554900043
              ],
              [
                -113.42740508584876,
                53.53540538545673
              ],
              [
                -113.42752998409404,
                53.535297565958665
              ],
              [
                -113.4279183488303,
                53.53523607037127
              ],
              [
                -113.42791996169746,
                53.535101584760206
              ],
              [
                -113.42805838398039,
                53.53496856727188
              ],
              [
                -113.42829752413948,
                53.53490378173595
              ],
              [
                -113.42853987634759,
                53.53492471565625
              ],
              [
                -113.42850919063734,
                53.534696689309655
              ],
              [
                -113.42878686237893,
                53.534536152700774
              ],
              [
                -113.42904941198546,
                53.53453081688118
              ],
              [
                -113.4292726905932,
                53.53461327921987
              ],
              [
                -113.42938144040319,
                53.53475574527003
              ],
              [
                -113.42932189227697,
                53.53492860047589
              ],
              [
                -113.43016090610413,
                53.53491381587701
              ],
              [
                -113.4303841888471,
                53.53499627608787
              ],
              [
                -113.43049370483175,
                53.535144180119
              ],
              [
                -113.4306827723688,
                53.53496953332378
              ],
              [
                -113.43048427160186,
                53.53480348112817
              ],
              [
                -113.43052958131928,
                53.53461129800268
              ],
              [
                -113.4302235170711,
                53.53452062437266
              ],
              [
                -113.43011173940162,
                53.53432534435993
              ],
              [
                -113.43017871323607,
                53.53420056688586
              ],
              [
                -113.43033650927543,
                53.534109331623945
              ],
              [
                -113.43074461728477,
                53.534082302056824
              ],
              [
                -113.43055398085168,
                53.53391948129028
              ],
              [
                -113.4305909552273,
                53.533736262126325
              ],
              [
                -113.43032999630488,
                53.53369632030702
              ],
              [
                -113.43014013655129,
                53.53355420730147
              ],
              [
                -113.43013117598197,
                53.53339779267695
              ],
              [
                -113.43024890874953,
                53.533276728162285
              ],
              [
                -113.42998515111661,
                53.53320580776352
              ],
              [
                -113.42984547889552,
                53.533044357950715
              ],
              [
                -113.42988791059724,
                53.53288990739333
              ],
              [
                -113.43004989173856,
                53.53278220699742
              ],
              [
                -113.42989839308662,
                53.53263677874835
              ],
              [
                -113.42991520994786,
                53.5324805940512
              ],
              [
                -113.43004009335186,
                53.532372772048184
              ],
              [
                -113.43027921585048,
                53.53230798271738
              ],
              [
                -113.43049769101988,
                53.532322772964946
              ],
              [
                -113.4306786671071,
                53.53239717542482
              ],
              [
                -113.43078741568463,
                53.532539640254626
              ],
              [
                -113.43073155189593,
                53.532708542486894
              ],
              [
                -113.43094854485314,
                53.532761503848626
              ],
              [
                -113.43108547946055,
                53.532864001292545
              ],
              [
                -113.43111082047011,
                53.533045005381574
              ],
              [
                -113.430955142871,
                53.53318621626255
              ],
              [
                -113.43121006086366,
                53.53334789042554
              ],
              [
                -113.43122833855824,
                53.533478438716635
              ],
              [
                -113.43113618168181,
                53.53360221269594
              ],
              [
                -113.43142276464697,
                53.53377088962632
              ],
              [
                -113.43138674272544,
                53.53399169530212
              ],
              [
                -113.43159704964464,
                53.534044202342685
              ],
              [
                -113.43175036795506,
                53.5341712884202
              ],
              [
                -113.43171772346665,
                53.53438846297076
              ],
              [
                -113.43180681150821,
                53.534411594667404
              ],
              [
                -113.43193357059783,
                53.5343002770938
              ],
              [
                -113.43217270085931,
                53.53423548390481
              ],
              [
                -113.43254124751822,
                53.5343056864791
              ],
              [
                -113.43268462624371,
                53.53449349594892
              ],
              [
                -113.43258753224666,
                53.53466948995921
              ],
              [
                -113.43291894764656,
                53.53480128032046
              ],
              [
                -113.4329789678079,
                53.534953646427745
              ],
              [
                -113.43289769437611,
                53.535090777910256
              ],
              [
                -113.43304740308224,
                53.53512861036126
              ],
              [
                -113.43330155912744,
                53.53494081643644
              ],
              [
                -113.43357951656051,
                53.534922407536
              ],
              [
                -113.43385011240672,
                53.534811158334854
              ],
              [
                -113.43429407707413,
                53.534798168164855
              ]
            ],
            [
              [
                -113.43214280141112,
                53.53479437335234
              ],
              [
                -113.43200819039687,
                53.53473650610702
              ],
              [
                -113.43187270973114,
                53.53485195900293
              ],
              [
                -113.43207979193858,
                53.5348983880322
              ],
              [
                -113.43214280141112,
                53.53479437335234
              ]
            ],
            [
              [
                -113.43126945833947,
                53.53491606727488
              ],
              [
                -113.43127985139981,
                53.53491677073159
              ],
              [
                -113.43127150771073,
                53.534914624150986
              ],
              [
                -113.43126945833947,
                53.53491606727488
              ]
            ],
            [
              [
                -113.42875022650362,
                53.53503758491781
              ],
              [
                -113.42880546902765,
                53.535205561070946
              ],
              [
                -113.42882807760039,
                53.535204438050194
              ],
              [
                -113.42893414646794,
                53.53506058946845
              ],
              [
                -113.42875022650362,
                53.53503758491781
              ]
            ]
          ],
          [
            [
              [
                -113.43531818763726,
                53.53563510968512
              ],
              [
                -113.43565535437736,
                53.53558796402943
              ],
              [
                -113.43594972746598,
                53.53569665780703
              ],
              [
                -113.43602886846791,
                53.5358975204251
              ],
              [
                -113.4358464151059,
                53.53607288969352
              ],
              [
                -113.43550924475716,
                53.5361200359253
              ],
              [
                -113.43521486979085,
                53.5360113410899
              ],
              [
                -113.43513573239757,
                53.53581047789575
              ],
              [
                -113.43531818763726,
                53.53563510968512
              ]
            ]
          ],
          [
            [
              [
                -113.42989274793446,
                53.52487937085289
              ],
              [
                -113.43017607038628,
                53.524812383706966
              ],
              [
                -113.43074165589066,
                53.52486897959308
              ],
              [
                -113.43094372804109,
                53.52503651983101
              ],
              [
                -113.43088780435622,
                53.525240133173064
              ],
              [
                -113.43056297399328,
                53.52536531756291
              ],
              [
                -113.42995313994474,
                53.52531091934841
              ],
              [
                -113.42980003211335,
                53.52521691004455
              ],
              [
                -113.42973937317046,
                53.52509099352153
              ],
              [
                -113.42989274793446,
                53.52487937085289
              ]
            ]
          ],
          [
            [
              [
                -113.42599870262559,
                53.53372076187676
              ],
              [
                -113.42619416259498,
                53.53366075110958
              ],
              [
                -113.42645632003267,
                53.53367077806423
              ],
              [
                -113.42663729504767,
                53.53374518664356
              ],
              [
                -113.42673802585642,
                53.533861634330385
              ],
              [
                -113.42673472362588,
                53.53399262135239
              ],
              [
                -113.42660640916091,
                53.53411979310675
              ],
              [
                -113.42677985958005,
                53.53434956995175
              ],
              [
                -113.42662251724157,
                53.534536911606374
              ],
              [
                -113.4267565836038,
                53.534654306154394
              ],
              [
                -113.42677484830176,
                53.53478485524622
              ],
              [
                -113.42665897393711,
                53.534925313967115
              ],
              [
                -113.42643164107284,
                53.535003748692546
              ],
              [
                -113.4260898661913,
                53.53497041213725
              ],
              [
                -113.4258877644057,
                53.534802864258914
              ],
              [
                -113.42590459666141,
                53.534646680004734
              ],
              [
                -113.42603408270654,
                53.53453668767572
              ],
              [
                -113.42590001870049,
                53.534419292288774
              ],
              [
                -113.42588175688343,
                53.53428874302433
              ],
              [
                -113.42601939052719,
                53.53413570618364
              ],
              [
                -113.42584594510375,
                53.53390592817203
              ],
              [
                -113.42599870262559,
                53.53372076187676
              ]
            ]
          ],
          [
            [
              [
                -113.42173161964878,
                53.5341390510285
              ],
              [
                -113.42205941687331,
                53.534072481531105
              ],
              [
                -113.42238461101121,
                53.53417427526892
              ],
              [
                -113.42272601246707,
                53.534070482640786
              ],
              [
                -113.42305029120325,
                53.53414291052705
              ],
              [
                -113.423193627688,
                53.534330731859015
              ],
              [
                -113.42302713620967,
                53.53454853326349
              ],
              [
                -113.4231942321372,
                53.53474833180801
              ],
              [
                -113.42307265881684,
                53.534941524060415
              ],
              [
                -113.42271298712797,
                53.535026518563605
              ],
              [
                -113.42240218028243,
                53.5349355025243
              ],
              [
                -113.42228976761395,
                53.534766666482895
              ],
              [
                -113.42245626373179,
                53.53454886606153
              ],
              [
                -113.42238718906569,
                53.53450712578404
              ],
              [
                -113.4220457832695,
                53.5346109174854
              ],
              [
                -113.42172150256066,
                53.53453848689934
              ],
              [
                -113.42157817180858,
                53.53435066374336
              ],
              [
                -113.42173161964878,
                53.5341390510285
              ]
            ]
          ],
          [
            [
              [
                -113.43299483330316,
                53.535616758208164
              ],
              [
                -113.43329968595484,
                53.53561946941768
              ],
              [
                -113.43355280058802,
                53.535760292597935
              ],
              [
                -113.43364937969423,
                53.53605064375877
              ],
              [
                -113.43349664780634,
                53.53623581948829
              ],
              [
                -113.43312472948138,
                53.536299434630116
              ],
              [
                -113.43288894325559,
                53.536230415271476
              ],
              [
                -113.43275089338138,
                53.53607430707498
              ],
              [
                -113.4323856497965,
                53.53619831535083
              ],
              [
                -113.43203041231683,
                53.53610692952358
              ],
              [
                -113.43191862197219,
                53.535911651387295
              ],
              [
                -113.43207135968969,
                53.53572647760163
              ],
              [
                -113.43239915198619,
                53.535659879804626
              ],
              [
                -113.43272706585505,
                53.535763653370566
              ],
              [
                -113.43299483330316,
                53.535616758208164
              ]
            ]
          ],
          [
            [
              [
                -113.4265003845153,
                53.53591086339678
              ],
              [
                -113.42682818745227,
                53.535844280768735
              ],
              [
                -113.42713901015529,
                53.53593528510551
              ],
              [
                -113.42725077869976,
                53.53613056795518
              ],
              [
                -113.42709801834394,
                53.53631573581813
              ],
              [
                -113.42677021223314,
                53.5363823192172
              ],
              [
                -113.42645938698548,
                53.53629131395506
              ],
              [
                -113.42634762161485,
                53.53609603033437
              ],
              [
                -113.4265003845153,
                53.53591086339678
              ]
            ]
          ]
        ]
      }
    }
  ]
}